mxmake/__init__.py
mxmake/_version.py
mxmake/helpgen.py
mxmake/hook.py
mxmake/main.py
mxmake/parser.py
mxmake/sphinxext.py
mxmake/templates.py
mxmake/topics.py
mxmake/utils.py
mxmake/templates/Makefile
mxmake/templates/additional_sources_targets.mk
mxmake/templates/dependencies.md
mxmake/templates/env.sh
mxmake/templates/gh-actions-docs.yml
mxmake/templates/gh-actions-lint.yml
mxmake/templates/gh-actions-test.yml
mxmake/templates/gh-actions-typecheck.yml
mxmake/templates/mx.ini
mxmake/templates/pip.conf
mxmake/templates/plone-site.py.tpl
mxmake/templates/proxy.mk
mxmake/templates/pytest-run-coverage.sh
mxmake/templates/pytest-run-tests.sh
mxmake/templates/script.sh
mxmake/templates/topics.md
mxmake/templates/zope-testrunner-run-coverage.sh
mxmake/templates/zope-testrunner-run-tests.sh
mxmake/testing/__init__.py
mxmake/tests/__init__.py
mxmake/tests/test_hook.py
mxmake/tests/test_parser.py
mxmake/tests/test_templates.py
mxmake/tests/test_topics.py
mxmake/tests/test_utils.py
mxmake/tests/expected/Makefile
mxmake/topics/applications/cookiecutter.mk
mxmake/topics/applications/metadata.ini
mxmake/topics/applications/plone.mk
mxmake/topics/applications/twisted.mk
mxmake/topics/applications/zest-releaser.mk
mxmake/topics/applications/zope.mk
mxmake/topics/core/base.mk
mxmake/topics/core/help.mk
mxmake/topics/core/metadata.ini
mxmake/topics/core/mxenv.mk
mxmake/topics/core/mxfiles.mk
mxmake/topics/core/packages.mk
mxmake/topics/core/proxy.mk
mxmake/topics/core/sources.mk
mxmake/topics/docs/jsdoc.mk
mxmake/topics/docs/metadata.ini
mxmake/topics/docs/sphinx.mk
mxmake/topics/i18n/gettext.mk
mxmake/topics/i18n/lingua.mk
mxmake/topics/i18n/metadata.ini
mxmake/topics/js/karma.mk
mxmake/topics/js/metadata.ini
mxmake/topics/js/nodejs.mk
mxmake/topics/js/rollup.mk
mxmake/topics/js/scss.mk
mxmake/topics/js/wtr.mk
mxmake/topics/ldap/metadata.ini
mxmake/topics/ldap/openldap.mk
mxmake/topics/ldap/python-ldap.mk
mxmake/topics/qa/black.mk
mxmake/topics/qa/coverage.mk
mxmake-2.1.0.dist-info/METADATA
mxmake-2.1.0.dist-info/WHEEL
mxmake-2.1.0.dist-info/entry_points.txt
mxmake-2.1.0.dist-info/licenses/LICENSE.md
mxmake-2.1.0.dist-info/RECORD
