Metadata-Version: 2.4
Name: mxmake
Version: 2.1.0
Summary: Generates a Python project-specific Makefile by using an extensible library of configurable Makefile snippets.
Project-URL: Homepage, https://github.com/mxstack/mxmake
Project-URL: Documentation, https://mxstack.github.io/mxmake
Project-URL: Bug Reports, https://github.com/mxstack/mxmake/issues
Project-URL: Source, https://github.com/mxstack/mxmake/tree/main
Author-email: MX Stack Developers <dev@bluedynamics.com>
License: BSD 2-Clause License
License-File: LICENSE.md
Keywords: deployment,development,make
Classifier: Development Status :: 5 - Production/Stable
Classifier: Intended Audience :: Developers
Classifier: License :: OSI Approved :: BSD License
Classifier: Operating System :: OS Independent
Classifier: Programming Language :: Python
Classifier: Programming Language :: Python :: 3.10
Classifier: Programming Language :: Python :: 3.11
Classifier: Programming Language :: Python :: 3.12
Classifier: Programming Language :: Python :: 3.13
Classifier: Programming Language :: Python :: 3.14
Classifier: Topic :: Software Development :: Build Tools
Requires-Python: >=3.10
Requires-Dist: inquirer
Requires-Dist: jinja2
Requires-Dist: mxdev>=4.0.2
Requires-Dist: pyyaml
Provides-Extra: docs
Requires-Dist: myst-parser; extra == 'docs'
Requires-Dist: shibuya; extra == 'docs'
Requires-Dist: sphinx>=7.2; extra == 'docs'
Requires-Dist: sphinxcontrib-mermaid; extra == 'docs'
Provides-Extra: test
Requires-Dist: coverage[toml]; extra == 'test'
Requires-Dist: pytest; extra == 'test'
